WuyunZhishikuDiyiBufenFix1/README.md
WuyunZhishikuDiyiBufenFix1/__init__.py
WuyunZhishikuDiyiBufenFix1/__main__.py
WuyunZhishikuDiyiBufenFix1/file.epub
WuyunZhishikuDiyiBufenFix1/index.html
WuyunZhishikuDiyiBufenFix1/css/__init__.py
WuyunZhishikuDiyiBufenFix1/css/annotations.css
WuyunZhishikuDiyiBufenFix1/css/main.css
WuyunZhishikuDiyiBufenFix1/css/normalize.css
WuyunZhishikuDiyiBufenFix1/css/popup.css
WuyunZhishikuDiyiBufenFix1/font/__init__.py
WuyunZhishikuDiyiBufenFix1/font/fontello.eot
WuyunZhishikuDiyiBufenFix1/font/fontello.svg
WuyunZhishikuDiyiBufenFix1/font/fontello.ttf
WuyunZhishikuDiyiBufenFix1/font/fontello.woff
WuyunZhishikuDiyiBufenFix1/img/__init__.py
WuyunZhishikuDiyiBufenFix1/img/annotator-glyph-sprite.png
WuyunZhishikuDiyiBufenFix1/img/annotator-icon-sprite.png
WuyunZhishikuDiyiBufenFix1/img/apple-touch-icon.png
WuyunZhishikuDiyiBufenFix1/img/cancelfullscreen.png
WuyunZhishikuDiyiBufenFix1/img/close.png
WuyunZhishikuDiyiBufenFix1/img/fullscreen.png
WuyunZhishikuDiyiBufenFix1/img/loader.gif
WuyunZhishikuDiyiBufenFix1/img/menu-icon.png
WuyunZhishikuDiyiBufenFix1/img/save.png
WuyunZhishikuDiyiBufenFix1/img/saved.png
WuyunZhishikuDiyiBufenFix1/img/settings-s.png
WuyunZhishikuDiyiBufenFix1/img/settings.png
WuyunZhishikuDiyiBufenFix1/img/star.png
WuyunZhishikuDiyiBufenFix1/js/__init__.py
WuyunZhishikuDiyiBufenFix1/js/epub.js
WuyunZhishikuDiyiBufenFix1/js/epub.min.js
WuyunZhishikuDiyiBufenFix1/js/epub.min.map
WuyunZhishikuDiyiBufenFix1/js/hooks.min.js
WuyunZhishikuDiyiBufenFix1/js/hooks.min.map
WuyunZhishikuDiyiBufenFix1/js/reader.js
WuyunZhishikuDiyiBufenFix1/js/reader.js.map
WuyunZhishikuDiyiBufenFix1/js/reader.min.js
WuyunZhishikuDiyiBufenFix1/js/reader.min.map
WuyunZhishikuDiyiBufenFix1/js/hooks/__init__.py
WuyunZhishikuDiyiBufenFix1/js/hooks/extensions/__init__.py
WuyunZhishikuDiyiBufenFix1/js/hooks/extensions/highlight.js
WuyunZhishikuDiyiBufenFix1/js/libs/__init__.py
WuyunZhishikuDiyiBufenFix1/js/libs/jquery.min.js
wuyun_zhishiku_diyi_bufen_fix1-2025.3.24.1.dist-info/METADATA
wuyun_zhishiku_diyi_bufen_fix1-2025.3.24.1.dist-info/WHEEL
wuyun_zhishiku_diyi_bufen_fix1-2025.3.24.1.dist-info/entry_points.txt
wuyun_zhishiku_diyi_bufen_fix1-2025.3.24.1.dist-info/top_level.txt
wuyun_zhishiku_diyi_bufen_fix1-2025.3.24.1.dist-info/RECORD
